{ "height":14,
 "layers":[
        {
         "data":[0, 0, 0, 0, 0, 0, 0, 0, 0, 0, 0, 0, 0, 0, 0, 0, 0, 0, 0, 0, 0, 0, 0, 0, 0, 0, 0, 0, 0, 0, 0, 0, 0, 0, 0, 0, 0, 0, 0, 0, 0, 0, 0, 0, 0, 0, 0, 0, 0, 0, 0, 0, 0, 0, 0, 0, 0, 0, 0, 0, 0, 0, 0, 0, 0, 0, 0, 0, 0, 0, 0, 0, 0, 0, 22, 0, 0, 0, 0, 22, 0, 0, 0, 0, 0, 0, 0, 0, 0, 0, 0, 0, 0, 22, 0, 0, 0, 0, 0, 0, 0, 0, 0, 0, 0, 0, 0, 0, 0, 22, 0, 0, 0, 0, 22, 0, 0, 0, 0, 0, 0, 22, 22, 22, 22, 0, 0, 0, 0, 0, 0, 22, 0, 0, 0, 0, 0, 0, 0, 0, 0, 0, 0, 0, 22, 22, 22, 0, 0, 22, 22, 22, 0, 0, 0, 0, 0, 0, 0, 0, 0, 0, 0, 22, 0, 0, 0, 0, 0, 0, 22, 0, 0, 0, 0, 0, 0, 22, 22, 22, 0, 0, 0, 0, 0, 0, 0, 0, 0, 0, 0, 0, 0, 0, 0, 0, 0, 0, 0, 0, 0, 22, 0, 0, 0, 0, 0, 0, 0, 0, 0, 0, 0, 0, 22, 0, 0, 0, 0, 0, 0, 0, 0, 0, 0, 0, 22, 0, 0, 22, 0, 0, 0, 0, 0, 0, 0, 0, 22, 0, 0, 0, 22, 0, 0, 0, 0, 0, 0, 0, 0, 0, 0, 0, 0, 0, 0, 0, 0, 0, 0, 22, 0, 0, 0, 0, 0, 0, 22, 0, 0, 0, 0, 0, 0, 0, 0, 0, 0, 0, 0, 0, 0, 0, 0, 0, 0, 0, 0, 22, 22, 22, 22, 0, 0, 0, 22, 0, 0, 0, 0, 0, 0, 0, 0, 0, 0, 0, 0, 0, 0, 0, 0, 0, 0, 0, 0, 0, 0, 0, 0, 0, 0, 0, 0, 0, 0, 22, 0, 0, 0, 0, 0, 0, 0, 0, 22, 0, 0, 0, 22, 0, 0, 0, 22, 0, 0, 0, 0, 0, 0, 0, 0, 0, 0, 0, 0, 0, 0, 0, 0, 0, 22, 0, 0, 0, 22, 22, 22, 0, 0, 0, 0, 0, 0, 0, 0, 0, 0, 0, 0, 0, 0, 0, 0, 0, 0, 0, 0, 22, 22, 22, 0, 0, 0, 0, 0, 22, 0, 0, 0, 0, 0, 22, 0, 0, 0, 0, 22, 0, 0, 0, 22, 0, 0, 0, 0, 22, 0, 0, 0, 0, 0, 0, 0, 0, 0, 0, 0, 0, 0, 0, 0, 0, 0, 0, 0, 0, 0, 0, 0, 0, 0, 0, 0, 0, 0, 0, 0, 0, 0, 0, 0, 0, 0, 0, 0, 0, 0, 0, 0, 0, 0, 0, 0, 0, 0, 0, 0, 0, 0, 0, 0, 0, 0, 0, 0, 0, 0, 0, 0, 0, 0, 0, 0, 0, 0, 0, 0, 0],
         "height":14,
         "name":"layer1",
         "opacity":1,
         "type":"tilelayer",
         "visible":true,
         "width":35,
         "x":0,
         "y":0
        }],
 "nextobjectid":1,
 "orientation":"orthogonal",
 "renderorder":"right-down",
 "tileheight":70,
 "tilesets":[
        {
         "columns":21,
         "firstgid":1,
         "image":"kenney.png",
         "imageheight":490,
         "imagewidth":1470,
         "margin":0,
         "name":"kenney",
         "spacing":0,
         "tilecount":147,
         "tileheight":70,
         "tileproperties":
            {
             "144":
                {
                 "slope":"1"
                },
             "18":
                {
                 "slope":"1"
                },
             "21":
                {
                 "slope":"1"
                },
             "49":
                {
                 "slope":"1"
                }
            },
         "tilepropertytypes":
            {
             "144":
                {
                 "slope":"string"
                },
             "18":
                {
                 "slope":"string"
                },
             "21":
                {
                 "slope":"string"
                },
             "49":
                {
                 "slope":"string"
                }
            },
         "tilewidth":70
        }],
 "tilewidth":70,
 "version":1,
 "width":35
}